HISTORY.md
LICENSE
README.md
datasafari/__init__.py
datasafari/evaluator/__init__.py
datasafari/evaluator/evaluate_contingency_table.py
datasafari/evaluator/evaluate_dtype.py
datasafari/evaluator/evaluate_normality.py
datasafari/evaluator/evaluate_variance.py
datasafari/explorer/__init__.py
datasafari/explorer/explore_cat.py
datasafari/explorer/explore_df.py
datasafari/explorer/explore_num.py
datasafari/predictor/__init__.py
datasafari/predictor/predict_hypothesis.py
datasafari/predictor/predict_ml.py
datasafari/transformer/__init__.py
datasafari/transformer/transform_cat.py
datasafari/transformer/transform_num.py
datasafari/utils/__init__.py
datasafari/utils/calculators.py
datasafari/utils/filters.py
docs/_static/css/rtd_dark.css
docs/_static/favicons/android-chrome-192x192.png
docs/_static/favicons/android-chrome-512x512.png
docs/_static/favicons/apple-touch-icon.png
docs/_static/favicons/ds-branding-favicon-original.png
docs/_static/favicons/favicon-16x16.png
docs/_static/favicons/favicon-32x32.png
docs/_static/logos/ds-branding-logo-big-darkmode.png
docs/_static/logos/ds-branding-logo-big-lightmode.png
docs/_static/logos/ds-branding-logo-small-darkmode.png
docs/_static/logos/unoptimized/ds-branding-logo-big-darkmode.png
docs/_static/logos/unoptimized/ds-branding-logo-big-lightmode.png
docs/_static/logos/unoptimized/ds-branding-logo-small-darkmode.png
docs/_static/my_logo.png
docs/_static/thumbs/ds-branding-thumb-main-docs.png
docs/_static/thumbs/ds-branding-thumb-main-github.png
docs/_static/thumbs/ds-branding-thumb-main-web.png
docs/_static/thumbs/ds-branding-thumb-sub-docs-evaluator.png
docs/_static/thumbs/ds-branding-thumb-sub-docs-explorer.png
docs/_static/thumbs/ds-branding-thumb-sub-docs-predictor.png
docs/_static/thumbs/ds-branding-thumb-sub-docs-transformer.png
docs/_static/thumbs/unoptimized/ds-branding-thumb-main-docs.png
docs/_static/thumbs/unoptimized/ds-branding-thumb-main-github.png
docs/_static/thumbs/unoptimized/ds-branding-thumb-main-web.png
datasafari-1.0.0.dist-info/AUTHORS.rst
datasafari-1.0.0.dist-info/LICENSE
datasafari-1.0.0.dist-info/METADATA
datasafari-1.0.0.dist-info/WHEEL
datasafari-1.0.0.dist-info/RECORD
