Metadata-Version: 2.1
Name: datasafari
Version: 1.0.0
Summary: DataSafari simplifies complex data science tasks into straightforward, powerful one-liners.
Home-page: https://www.datasafari.dev
License: GPL-3.0-only
Keywords: data science,data analysis,machine learning,data preprocessing,statistical testing,data transformation,predictive modeling,data visualization,exploratory data analysis,hypothesis testing,feature engineering,model evaluation,model tuning,data cleaning,data insights,numerical analysis,categorical data,statistics,ML automation,data workflow,data discovery,sklearn integration,statistical inference,automated machine learning,data exploration
Author: George Dreemer
Author-email: georgedreemer@proton.me
Requires-Python: >=3.9,<4.0
Classifier: Development Status :: 5 - Production/Stable
Classifier: Intended Audience :: Developers
Classifier: License :: OSI Approved :: GNU General Public License v3 (GPLv3)
Classifier: Natural Language :: English
Classifier: Programming Language :: Python :: 3
Classifier: Programming Language :: Python :: 3.9
Classifier: Programming Language :: Python :: 3.10
Classifier: Programming Language :: Python :: 3.11
Classifier: Programming Language :: Python :: 3.12
Requires-Dist: category-encoders
Requires-Dist: matplotlib
Requires-Dist: numpy
Requires-Dist: pandas
Requires-Dist: python-Levenshtein
Requires-Dist: scikit-learn (<1.5)
Requires-Dist: scikit-optimize (>=0.10.1)
Requires-Dist: scipy
Requires-Dist: seaborn
Requires-Dist: statsmodels
Project-URL: Documentation, https://www.datasafari.dev/docs
Project-URL: Repository, https://github.com/ETA444/datasafari
